[
  {"COMMENT": "GENKI LESSON 03"},
  {
    "id": "0000d0db-623b-457d-b797-5c7bfd8d0000",
    "title": "〜ませんか",
    "meaning": "to extend an invitation",
    "how_to_use": [
      "verb + ませんか"
    ],
    "examples": [
      {
        "id": "aaaa2051-aab0-494e-b0ff-4be24feaaaaa",
        "meaning": "What do you say to having lunch with me?",
        "text": {
          "spelling": "{昼|ひる}ご{飯|はん}を{食|た}べませんか。",
          "phonetic_spelling": null
        },
        "lesson_codes": ["GENKI3_L03"],
        "tags": []
      },
      {
        "id": "bbbb2051-aab0-494e-b0ff-4be24feabbbb",
        "meaning": "Will you play tennis with me?",
        "text": {
          "spelling": "テニスをませんか。",
          "phonetic_spelling": null
        },
        "lesson_codes": ["GENKI3_L03"],
        "tags": []
      }
    ],
    "jlpt_level": null,
    "date_added": "2023-03-09",
    "lesson_codes": ["GENKI3_L03"],
    "tags": []
  },
  {"COMMENT": "GENKI LESSON 04"},
  {
    "id": "3a5e1272-f03e-4ac4-89be-ad06b7a3331d",
    "title": "Ａがあります",
    "meaning": "I have/own A (inanimate)",
    "how_to_use": [
      "thing + が + あります"
    ],
    "examples": [
      {
        "id": "06c8e3e4-ccfb-4646-bb6c-b83bf6128369",
        "meaning": "I don't have a TV.",
        "text": {
          "spelling": "テレビがありません。",
          "phonetic_spelling": null
        },
        "lesson_codes": ["GENKI3_L04"],
        "tags": []
      },
      {
        "id": "8cf7fb0c-0f5b-488a-8c55-17265162cc04",
        "meaning": "Do you have time?",
        "text": {
          "spelling": "{時|じ}{間|かん}がありますか。",
          "phonetic_spelling": null
        },
        "lesson_codes": ["GENKI3_L04"],
        "tags": []
      }
    ],
    "jlpt_level": null,
    "date_added": "2023-03-09",
    "lesson_codes": ["GENKI3_L04"],
    "tags": []
  },
  {
    "id": "b69d0d83-ae0e-4834-abaf-9c570c976d00",
    "title": "Ａがいます",
    "meaning": "I have/own A (animate)",
    "how_to_use": [
      "thing + が + います"
    ],
    "examples": [
      {
        "id": "29a6b9a0-2b3b-42fb-9d49-835fdd2ca505",
        "meaning": "I have a Japanese friend.",
        "text": {
          "spelling": "{日本|に・ほん}{人|じん}の{友達|とも・だち}がいます。",
          "phonetic_spelling": null
        },
        "lesson_codes": ["GENKI3_L04"],
        "tags": []
      }
    ],
    "jlpt_level": null,
    "date_added": "2023-03-09",
    "lesson_codes": ["GENKI3_L04"],
    "tags": []
  },
  {
    "id": "5120aeab-2b79-4837-9461-1bc174684feb",
    "title": "ＡにＢがあります",
    "meaning": "There is/are B at A (inanimate)",
    "how_to_use": [
      "place + に + thing + が + あります"
    ],
    "examples": [
      {
        "id": "49ec76a6-272e-4749-acb8-e46d0617bedd",
        "meaning": "There's a McDonald's Over There.",
        "text": {
          "spelling": "あぞこにマクドナルドがあります。",
          "phonetic_spelling": null
        },
        "lesson_codes": ["GENKI3_L04"],
        "tags": []
      },
      {
        "id": "e499c4cc-8bba-458b-a3b0-1dfe742951f3",
        "meaning": "There will be no Japanese class tomorrow",
        "text": {
          "spelling": "{明|あ}{日|した}は{日|に}{本|ほん}{語|ご}のクラスがありません。",
          "phonetic_spelling": null
        },
        "lesson_codes": ["GENKI3_L04"],
        "tags": []
      }
    ],
    "jlpt_level": null,
    "date_added": "2023-03-09",
    "lesson_codes": ["GENKI3_L04"],
    "tags": []
  },
  {
    "id": "17184226-f266-4972-b24a-3f34ee7ebb6b",
    "title": "ＡにＢがいます",
    "meaning": "There is/are B at A (animate)",
    "how_to_use": [
      "place + に + thing + が + あいます"
    ],
    "examples": [
      {
        "id": "48a00293-3121-4ccc-9b3e-d4998a74f6c2",
        "meaning": "There's an international student over there.",
        "text": {
          "spelling": "あそこに{留学生|りゅう・がく・せい}がいます。",
          "phonetic_spelling": null
        },
        "lesson_codes": ["GENKI3_L04"],
        "tags": []
      }
    ],
    "jlpt_level": null,
    "date_added": "2023-03-09",
    "lesson_codes": ["GENKI3_L04"],
    "tags": []
  },
  {
    "id": "0f175278-c567-4806-bad4-4cd040c40ad9",
    "title": "ＡはＢのＬです",
    "meaning": "A is {location word} of/to B",
    "how_to_use": [
      "noun + は + noun + の + 右 + です",
      "noun + は + noun + の + 左 + です",
      "noun + は + noun + の + 前 + です",
      "noun + は + noun + の + 後ろ + です",
      "noun + は + noun + の + 中 + です",
      "noun + は + noun + の + 上 + です",
      "noun + は + noun + の + 下 + です",
      "noun + は + noun + の + 違く + です",
      "noun + は + noun + の + 隣 + です"
    ],
    "examples": [
      {
        "id": "b63bb0cc-5bb9-4453-9c07-f097b49743c7",
        "meaning": "The bank is next to the library.",
        "text": {
          "spelling": "{銀行|ぎん・こう}は{図書館|と・しょ・かん}の{隣|となり}です。",
          "phonetic_spelling": null
        },
        "lesson_codes": ["GENKI3_L03"],
        "tags": []
      },
      {
        "id": "b318cbf3-3ead-4b44-b399-9a72dae9636b",
        "meaning": "I waited for Mary in front of the Mos Burger place.",
        "text": {
          "spelling": "{私|わたし}はモスバーガーの{前|まえ}でメアリーさんを{待|ま}ちました。",
          "phonetic_spelling": null
        },
        "lesson_codes": ["GENKI3_L03"],
        "tags": []
      },
      {
        "id": "7f604d44-ff48-4546-a17b-eead1f511b26",
        "meaning": "The umbrella is under the table.",
        "text": {
          "spelling": "{傘|かさ}はテーブルの{下|した}です。",
          "phonetic_spelling": null
        },
        "lesson_codes": ["GENKI3_L03"],
        "tags": []
      }
    ],
    "jlpt_level": null,
    "date_added": "2023-03-09",
    "lesson_codes": ["GENKI3_L03"],
    "tags": []
  },
  {
    "id": "11f50022-8091-40d0-831a-de86193f2f8d",
    "title": "ＡはＢとＣの間です",
    "meaning": "A is between B and C",
    "how_to_use": [
      "noun + は + noun + と + noun + の + 間です"
    ],
    "examples": [
      {
        "id": "0e15c2a9-4690-4969-8c69-2b1df5b395ad",
        "meaning": "The restaurant is between the supermarket and the hospital.",
        "text": {
          "spelling": "レストランはスーパーと{病院|びょう・いん}の{間|あいだ}です",
          "phonetic_spelling": null
        },
        "lesson_codes": ["GENKI3_L03"],
        "tags": []
      }
    ],
    "jlpt_level": null,
    "date_added": "2023-03-09",
    "lesson_codes": ["GENKI3_L03"],
    "tags": []
  },
  {
    "id": "5fe8f0bb-9572-4a81-88a6-7a83d554b85d",
    "title": "〜時間",
    "meaning": "duration of time",
    "how_to_use": [
      "number + 時間",
      "number + 時間 + ぐらい",
      "number + 時間 + 半"
    ],
    "examples": [
      {
        "id": "3431e3f2-8cd4-49a7-bdd6-afc907ea8063",
        "meaning": "Mary waited for Takeshi there for an hour and a half.",
        "text": {
          "spelling": "メアリーさんはそこでたけしさんを{一|いち}{時間|じ・かん}{半|はん}{待|ま}ちました。",
          "phonetic_spelling": null
        },
        "lesson_codes": ["GENKI3_L04"],
        "tags": []
      },
      {
        "id": "b4dd90bd-4073-47c6-93c8-81099a896be6",
        "meaning": "I studied Japanes for about three hours yesterday.",
        "text": {
          "spelling": "{私|わたし}は{昨日|きのう}{日本語|に・ほん・ご}を{三|さん}{時間|じ・かん}ぐらい{勉強|べん・きょう}しました。",
          "phonetic_spelling": null
        },
        "lesson_codes": ["GENKI3_L04"],
        "tags": []
      }
    ],
    "jlpt_level": null,
    "date_added": "2023-03-10",
    "lesson_codes": ["GENKI3_L04"],
    "tags": []
  },
  {
    "id": "a4766a9c-8bc7-446b-b0df-c3e2865612df",
    "title": "ＡとＢ",
    "meaning": "A and B; person A together with person B",
    "how_to_use": [
      "noun + と + noun",
      "person + は + person + と"
    ],
    "examples": [
      {
        "id": "9bc46693-0629-4ba0-9cc3-8eba36fe53a0",
        "meaning": "I went to Kyoto and Osaka.",
        "text": {
          "spelling": "{京都|きょう・と}と{大阪|おお・さか}に{行|い}きました。",
          "phonetic_spelling": null
        },
        "lesson_codes": ["GENKI3_L04"],
        "tags": []
      },
      {
        "id": "a5e2bbf1-e72f-4523-8c64-117ca89c6637",
        "meaning": "Mary will go to Korea with Sora",
        "text": {
          "spelling": "メアリーさんはそらさんと{韓国|かん・こく}に{行|い}きます。",
          "phonetic_spelling": null
        },
        "lesson_codes": ["GENKI3_L04"],
        "tags": []
      }
    ],
    "jlpt_level": null,
    "date_added": "2023-03-09",
    "lesson_codes": ["GENKI3_L04"],
    "tags": []
  },
  {"COMMENT": "GENKI LESSON 05"},
  {
    "id": "ab1cd527-1492-4657-8d6e-0905ca0154ca",
    "title": "Ａ(な)Ｎ",
    "meaning": "Adjective Noun Modification",
    "how_to_use": [
      "い-adj + noun",
      "な-adj + な　+ noun"
    ],
    "examples": [
      {
        "id": "3180b40e-58b7-4227-87ca-d52d5885fa7d",
        "meaning": "I saw an interesting movie yesterday.",
        "text": {
          "spelling": "{昨日|きのう}、{面白|おも・しろ}い{映画|えい・が}を{見|み}ました。",
          "phonetic_spelling": null
        },
        "lesson_codes": ["GENKI3_L05"],
        "tags": []
      },
      {
        "id": "aeda3553-aeaf-4932-8236-94071acbc396",
        "meaning": "I took a beautiful picture in Kyoto.",
        "text": {
          "spelling": "{京都|きょう・と}できれいな{写真|しゃ・しん}を{撮|と}りました。",
          "phonetic_spelling": null
        },
        "lesson_codes": ["GENKI3_L05"],
        "tags": []
      },
      {
        "id": "ad7ac198-73d3-4a09-9105-81eee35dd9da",
        "meaning": "This is a very vibrant city.",
        "text": {
          "spelling": "ここはとても{賑|にぎ}やかな{町|まち}です。",
          "phonetic_spelling": null
        },
        "lesson_codes": ["GENKI3_L05"],
        "tags": []
      }
    ],
    "jlpt_level": null,
    "date_added": "2023-03-23",
    "lesson_codes": ["GENKI3_L05"],
    "tags": []
  },
  {
    "id": "d9bdda30-d7bd-470e-a2c5-ac0d08c56fb6",
    "title": "〜ましょう",
    "meaning": "Let's...",
    "how_to_use": [
      "verb-stem + ましょう"
    ],
    "examples": [
      {
        "id": "bb888773-2128-4246-93ca-df94112ff45f",
        "meaning": "Let's study in the library together.",
        "text": {
          "spelling": "{一緒|いっ・しょ}に{図書館|と・しょ・かん}で{勉強|べん・きょう}しましょう",
          "phonetic_spelling": null
        },
        "lesson_codes": ["GENKI3_L05"],
        "tags": []
      },
      {
        "id": "7bec1b6a-784d-443c-a379-aeb412ec83c1",
        "meaning": "Let's go eat together.",
        "text": {
          "spelling": "{一緒|いっ・しょ}に{食|た}べに{行|い}きましょう",
          "phonetic_spelling": null
        },
        "lesson_codes": [],
        "tags": []
      }
    ],
    "jlpt_level": null,
    "date_added": "2023-03-23",
    "lesson_codes": ["GENKI3_L05"],
    "tags": []
  },
  {
    "id": "30a31f32-839f-4610-baf8-788a7f390fd2",
    "title": "〜ましょうか",
    "meaning": "shall I... / let me do ...",
    "how_to_use": [
      "verb-stem + ましょうか"
    ],
    "examples": [
      {
        "id": "b6465b41-5ce4-4d46-8b15-16780877262e",
        "meaning": "Shall we drink coffee over there?",
        "text": {
          "spelling": "あそこでコーヒーを{飲|の}みましょうか。",
          "phonetic_spelling": null
        },
        "lesson_codes": ["GENKI3_L05"],
        "tags": []
      },
      {
        "id": "90bdc4bd-0f06-454d-9168-304d589cd8f2",
        "meaning": "Shall I take a picture for you?",
        "text": {
          "spelling": "{写真|しゃ・しん}を{撮|と}りましょうか。",
          "phonetic_spelling": null
        },
        "lesson_codes": ["JLPT_SENSEI_GRAMMAR_N5"],
        "tags": []
      },
      {
        "id": "df095a25-8c61-420f-b923-19f2b756daac",
        "meaning": "Shall I carry your bag?",
        "text": {
          "spelling": "{荷物|に・もつ}を{持|も}ちましょうか。",
          "phonetic_spelling": null
        },
        "lesson_codes": ["GENKI3_L06"],
        "tags": []
      }
    ],
    "jlpt_level": null,
    "date_added": "2023-03-23",
    "lesson_codes": ["GENKI3_L05", "GENKI3_L06"],
    "tags": []
  },
  {"COMMENT": "GENKI LESSON 06"},
  {
    "id": "6d942fcf-dc23-4adb-aa88-6bc8ab197ff3",
    "title": "〜てください",
    "meaning": "please do ... for me",
    "how_to_use": [
      "verb(て　form) + ください"
    ],
    "examples": [
      {
        "id": "96f641ac-ce4a-4da2-b980-76b63aa7398c",
        "meaning": "Please read the textbook.",
        "text": {
          "spelling": "{教科書|きょう・か・しょ}を{読|よ}んでください。",
          "phonetic_spelling": null
        },
        "lesson_codes": ["GENKI3_L06"],
        "tags": []
      },
      {
        "id": "78e69786-38e1-4c5f-b4f5-5e649c3ba576",
        "meaning": "Excuse me. Please teach me a a little.",
        "text": {
          "spelling": "すみません。ちょうと{教|おし}えてください。",
          "phonetic_spelling": null
        },
        "lesson_codes": ["GENKI3_L06"],
        "tags": []
      }
    ],
    "jlpt_level": null,
    "date_added": "2023-04-09",
    "lesson_codes": ["GENKI3_L06"],
    "tags": []
  },
  {
    "id": "1b6c21c5-298b-47b1-bce9-295970b3ca3f",
    "title": "Ａて、Ｂ。",
    "meaning": "to do A and do B",
    "how_to_use": [
      "verb (て form) + 、+ verb"
    ],
    "examples": [
      {
        "id": "96483b58-c1ee-49ee-a0fb-10961b8d52a3",
        "meaning": "I will go to the library and check out some books.",
        "text": {
          "spelling": "{図書館|と・しょ・かん}に{行|い}って、本を{借|か}ります。",
          "phonetic_spelling": null
        },
        "lesson_codes": ["GENKI3_L06"],
        "tags": []
      },
      {
        "id": "14c95ee9-570f-4d67-8d7d-b4286ca2c0ad",
        "meaning": "Today I got up at six and studied.",
        "text": {
          "spelling": "{今日|きょう}は、{六|ろく}{時|じ}に{起|お}きて、{勉強|べん・きょう}しました。",
          "phonetic_spelling": null
        },
        "lesson_codes": ["GENKI3_L06"],
        "tags": []
      },
      {
        "id": "4a77c196-3b0a-4c70-89b4-17f72c1e0140",
        "meaning": "Let's go to the cafeteria and have lunch.",
        "text": {
          "spelling": "{食堂|しょく・どう}に{行|い}って、{昼|ひる}ご{飯|はん}を{食|た}べましよう。",
          "phonetic_spelling": null
        },
        "lesson_codes": ["GENKI3_L06"],
        "tags": []
      }
    ],
    "jlpt_level": null,
    "date_added": "2023-04-09",
    "lesson_codes": ["GENKI3_L06"],
    "tags": []
  },
  {
    "id": "79fb54a3-79c7-4691-9d3d-f0ea459c3b9a",
    "title": "〜てもいいです",
    "meaning": "you may do ...",
    "how_to_use": [
      "verb (て form) + もいいです"
    ],
    "examples": [
      {
        "id": "6d85da21-e530-49d4-a4ef-7a457d991916",
        "meaning": "You may use the textbook.",
        "text": {
          "spelling": "{教科書|きょう・か・しょ}を{見|み}てもいいですよ。",
          "phonetic_spelling": null
        },
        "lesson_codes": ["GENKI3_L06"],
        "tags": []
      },
      {
        "id": "3ec1dc21-bd84-4b61-a081-653ed46a7b17",
        "meaning": "May I go to the bathroom? You may./Please.",
        "text": {
          "spelling": "トイレに{行|い}ってもいいですか。はい、いいですよ。／どうぞ。",
          "phonetic_spelling": null
        },
        "lesson_codes": ["GENKI3_L06"],
        "tags": []
      }
    ],
    "jlpt_level": null,
    "date_added": "2023-04-09",
    "lesson_codes": ["GENKI3_L06"],
    "tags": []
  },
  {
    "id": "45d46c59-d86c-4a19-9e53-3cebf4dbae83",
    "title": "〜てはいけません",
    "meaning": "you must not do ...",
    "how_to_use": [
      "verb (て form) + はいけません",
      "verb (て form) + はいけない"
    ],
    "examples": [
      {
        "id": "ff742105-6ca3-444b-986f-bcae6765af32",
        "meaning": "You must not take pictures here.",
        "text": {
          "spelling": "ここで{写真|しゃ・しん}を{撮|と}って{は|wa}いけません。",
          "phonetic_spelling": null
        },
        "lesson_codes": ["GENKI3_L06"],
        "tags": []
      },
      {
        "id": "d538ef36-049b-421b-b182-745d3730a9f5",
        "meaning": "Do not open up the window.",
        "text": {
          "spelling": "{窓|まど}を{開|あ}けて{は|wa}いけない。",
          "phonetic_spelling": null
        },
        "lesson_codes": ["JLPT_SENSEI_GRAMMAR_N5"],
        "tags": []
      }
    ],
    "jlpt_level": null,
    "date_added": "2023-04-09",
    "lesson_codes": ["GENKI3_L06","JLPT_SENSEI_GRAMMAR_N5"],
    "tags": []
  },
  {
    "id": "c5381ae9-d2a9-43fb-836a-53d02a300edf",
    "title": "Ａ。Ｂから。",
    "meaning": "A; because B",
    "how_to_use": [
      "(situation)。 (explanation)から。"
    ],
    "examples": [
      {
        "id": "8059e232-04da-4512-8734-762c9c42d67d",
        "meaning": "I will study this evening. (Because) we will have an exam tomorrow.",
        "text": {
          "spelling": "{私|わたし}は{今晩|こん・ばん}{勉強|べん・きょう}します。あしたテストがありますから。",
          "phonetic_spelling": null
        },
        "lesson_codes": ["GENKI3_L06"],
        "tags": []
      },
      {
        "id": "f75e83dc-5ab0-43f5-ace0-f80fffda18a5",
        "meaning": "Let's go by bus. (Because) taxis are expensive.",
        "text": {
          "spelling": "バスに{乗|の}りましょう。タクシーは{高|たか}いですから。",
          "phonetic_spelling": null
        },
        "lesson_codes": ["GENKI3_L06"],
        "tags": []
      }
    ],
    "jlpt_level": null,
    "date_added": "2023-04-09",
    "lesson_codes": ["GENKI3_L06"],
    "tags": []
  }
]
